{
  "current_temp": null,
  "current_wind": null,
  "temp_flag": "warm",
  "avg_temp": 26.271428571428572,
  "max_temp": 38.2,
  "min_temp": 14.0,
  "temp_variability": 24.200000000000003,
  "avg_humidity": null,
  "max_wind": null,
  "adverse_weather": true,
  "weekly_forecast": [
    {
      "date": "2025-06-24",
      "max_temp": 38.2,
      "min_temp": 24.6,
      "precipitation": 0.0,
      "weathercode": 2
    },
    {
      "date": "2025-06-25",
      "max_temp": 33.6,
      "min_temp": 22.4,
      "precipitation": 0.4,
      "weathercode": 51
    },
    {
      "date": "2025-06-26",
      "max_temp": 22.7,
      "min_temp": 14.4,
      "precipitation": 3.4,
      "weathercode": 61
    },
    {
      "date": "2025-06-27",
      "max_temp": 18.2,
      "min_temp": 14.5,
      "precipitation": 0.3,
      "weathercode": 51
    },
    {
      "date": "2025-06-28",
      "max_temp": 15.6,
      "min_temp": 14.4,
      "precipitation": 24.6,
      "weathercode": 81
    },
    {
      "date": "2025-06-29",
      "max_temp": 23.1,
      "min_temp": 14.0,
      "precipitation": 0.0,
      "weathercode": 45
    },
    {
      "date": "2025-06-30",
      "max_temp": 32.5,
      "min_temp": 14.9,
      "precipitation": 0.0,
      "weathercode": 1
    }
  ],
  "avg_max_temp": 26.271428571428572,
  "avg_min_temp": 17.028571428571432,
  "total_precip": 28.700000000000003
}